{"frames": {

"BlueSpell14_0.png":
{
	"frame": {"x":0,"y":0,"w":32,"h":32},
	"rotated": false,
	"trimmed": false,
	"spriteSourceSize": {"x":0,"y":0,"w":32,"h":32},
	"sourceSize": {"w":32,"h":32}
},
"BlueSpell14_1.png":
{
	"frame": {"x":32,"y":0,"w":32,"h":32},
	"rotated": false,
	"trimmed": false,
	"spriteSourceSize": {"x":0,"y":0,"w":32,"h":32},
	"sourceSize": {"w":32,"h":32}
},
"BlueSpell14_2.png":
{
	"frame": {"x":64,"y":0,"w":32,"h":32},
	"rotated": false,
	"trimmed": false,
	"spriteSourceSize": {"x":0,"y":0,"w":32,"h":32},
	"sourceSize": {"w":32,"h":32}
},
"BlueSpell14_3.png":
{
	"frame": {"x":96,"y":0,"w":32,"h":32},
	"rotated": false,
	"trimmed": false,
	"spriteSourceSize": {"x":0,"y":0,"w":32,"h":32},
	"sourceSize": {"w":32,"h":32}
},
"BlueSpell14_4.png":
{
	"frame": {"x":128,"y":0,"w":32,"h":32},
	"rotated": false,
	"trimmed": false,
	"spriteSourceSize": {"x":0,"y":0,"w":32,"h":32},
	"sourceSize": {"w":32,"h":32}
},
"BlueSpell14_5.png":
{
	"frame": {"x":160,"y":0,"w":32,"h":32},
	"rotated": false,
	"trimmed": false,
	"spriteSourceSize": {"x":0,"y":0,"w":32,"h":32},
	"sourceSize": {"w":32,"h":32}
}},
"animations": {
	"BlueSpell14": ["BlueSpell14_0.png","BlueSpell14_1.png","BlueSpell14_2.png","BlueSpell14_3.png","BlueSpell14_4.png","BlueSpell14_5.png"]
},
"meta": {
	"app": "https://www.codeandweb.com/texturepacker",
	"version": "1.1",
	"image": "BlueSpell14.png",
	"format": "RGBA8888",
	"size": {"w":192,"h":32},
	"scale": "1",
	"smartupdate": "$TexturePacker:SmartUpdate:4fa1ec4c4b5438261fdb1d156a97c058:6537ba905b03f3b9f56ae5205a13650e:2cca8ba2614941bf422e9692d560fcff$"
}
}
